perceiver_io/__init__.py
perceiver_io/attention.py
perceiver_io/decoders.py
perceiver_io/encoder.py
perceiver_io/perceiver.py
perceiver_io/positional_encoding.py
perceiver_io_pytorch-0.1.5.dist-info/LICENSE
perceiver_io_pytorch-0.1.5.dist-info/METADATA
perceiver_io_pytorch-0.1.5.dist-info/WHEEL
perceiver_io_pytorch-0.1.5.dist-info/top_level.txt
perceiver_io_pytorch-0.1.5.dist-info/RECORD
