Metadata-Version: 2.1
Name: perceiver-io-pytorch
Version: 0.1.5
Summary: Unofficial Perceiver IO implementation
Home-page: https://github.com/esceptico/perceiver-io
Author: Timur Ganiev
Author-email: ganiev.tmr@gmail.com
License: MIT
License-File: LICENSE
Requires-Dist: torch
